anaml_client/__init__.py
anaml_client/exceptions.py
anaml_client/version.py
anaml_client/models/__init__.py
anaml_client/models/access_control/__init__.py
anaml_client/models/aggregate/__init__.py
anaml_client/models/anaml_object/__init__.py
anaml_client/models/attribute/__init__.py
anaml_client/models/batch_output_mode/__init__.py
anaml_client/models/branch/__init__.py
anaml_client/models/branch_protection/__init__.py
anaml_client/models/checks/__init__.py
anaml_client/models/cluster/__init__.py
anaml_client/models/cluster_creation_request/__init__.py
anaml_client/models/commit/__init__.py
anaml_client/models/created_updated/__init__.py
anaml_client/models/credentials_provider_config/__init__.py
anaml_client/models/dashboard/__init__.py
anaml_client/models/date_range/__init__.py
anaml_client/models/destination/__init__.py
anaml_client/models/destination_creation_request/__init__.py
anaml_client/models/destination_reference/__init__.py
anaml_client/models/entity/__init__.py
anaml_client/models/entity_creation_request/__init__.py
anaml_client/models/entity_mapping/__init__.py
anaml_client/models/entity_mapping_creation_request/__init__.py
anaml_client/models/entity_population/__init__.py
anaml_client/models/event/__init__.py
anaml_client/models/event_description/__init__.py
anaml_client/models/event_store/__init__.py
anaml_client/models/event_store_creation_request/__init__.py
anaml_client/models/event_window/__init__.py
anaml_client/models/feature/__init__.py
anaml_client/models/feature_creation_request/__init__.py
anaml_client/models/feature_id/__init__.py
anaml_client/models/feature_run_summaries/__init__.py
anaml_client/models/feature_set/__init__.py
anaml_client/models/feature_set_creation_request/__init__.py
anaml_client/models/feature_store/__init__.py
anaml_client/models/feature_store_creation_request/__init__.py
anaml_client/models/feature_store_run/__init__.py
anaml_client/models/feature_template/__init__.py
anaml_client-0.33.0.dist-info/METADATA
anaml_client-0.33.0.dist-info/WHEEL
anaml_client-0.33.0.dist-info/top_level.txt
anaml_client-0.33.0.dist-info/RECORD
